mlgidGUI/__init__.py
mlgidGUI/__main__.py
mlgidGUI/__version.py
mlgidGUI/app/__init__.py
mlgidGUI/app/actions_stack.py
mlgidGUI/app/app.py
mlgidGUI/app/debug_tracker.py
mlgidGUI/app/edf_reader.py
mlgidGUI/app/geometry.py
mlgidGUI/app/geometry_holder.py
mlgidGUI/app/image_holder.py
mlgidGUI/app/image_processing.py
mlgidGUI/app/polar_image.py
mlgidGUI/app/read_image.py
mlgidGUI/app/transformations.py
mlgidGUI/app/utils.py
mlgidGUI/app/cif_rois/__init__.py
mlgidGUI/app/cif_rois/cif_peaks_calculation.py
mlgidGUI/app/cif_rois/cif_simulation/__init__.py
mlgidGUI/app/cif_rois/cif_simulation/experiment.py
mlgidGUI/app/cif_rois/cif_simulation/giwaxs_sim.py
mlgidGUI/app/cif_rois/cif_simulation/int_sim.py
mlgidGUI/app/cif_rois/cif_simulation/possible_directions.py
mlgidGUI/app/cif_rois/cif_simulation/q_sim.py
mlgidGUI/app/cif_rois/cif_simulation/data/__init__.py
mlgidGUI/app/cif_rois/cif_simulation/data/atoms.py
mlgidGUI/app/cif_rois/cif_simulation/data/export_database.py
mlgidGUI/app/data_manager/__init__.py
mlgidGUI/app/data_manager/data_manager.py
mlgidGUI/app/data_manager/import_from_h5.py
mlgidGUI/app/data_manager/load_data.py
mlgidGUI/app/data_manager/save_dataset.py
mlgidGUI/app/data_manager/save_h5.py
mlgidGUI/app/data_manager/saving_parameters.py
mlgidGUI/app/data_manager/pascal/__init__.py
mlgidGUI/app/data_manager/pascal/annotation_fabric.py
mlgidGUI/app/data_manager/pascal/draw_objects.py
mlgidGUI/app/data_manager/pascal/exceptions.py
mlgidGUI/app/data_manager/pascal/format_convertor.py
mlgidGUI/app/data_manager/pascal/pascal_annotation.py
mlgidGUI/app/data_manager/pascal/protocol_implementations.py
mlgidGUI/app/data_manager/pascal/protocols.py
mlgidGUI/app/data_manager/pascal/utils.py
mlgidGUI/app/file_manager/__init__.py
mlgidGUI/app/file_manager/config_manager.py
mlgidGUI/app/file_manager/keys.py
mlgidGUI/app/file_manager/npy_file_manager.py
mlgidGUI/app/file_manager/object_file_manager.py
mlgidGUI/app/file_manager/project_structure.py
mlgidgui-0.6.2.dist-info/licenses/LICENSE
mlgidgui-0.6.2.dist-info/METADATA
mlgidgui-0.6.2.dist-info/WHEEL
mlgidgui-0.6.2.dist-info/entry_points.txt
mlgidgui-0.6.2.dist-info/top_level.txt
mlgidgui-0.6.2.dist-info/RECORD
