Metadata-Version: 2.4
Name: mlgidGUI
Version: 0.6.2
Summary: A GUI program for GIWAXS images analysis and annotation
Author-email: Constantin Völter <constantin.voelter@gmail.com>, Vladimir Starostin <v.starostin.m@gmail.com>
License-Expression: GPL-3.0-or-later
Project-URL: Homepage, https://github.com/mlgid-project/mlgidGUI
Keywords: xray,python,giwaxs,scientific-analysis
Classifier: Programming Language :: Python :: 3
Classifier: Operating System :: OS Independent
Classifier: Intended Audience :: Science/Research
Classifier: Topic :: Scientific/Engineering :: Artificial Intelligence
Classifier: Topic :: Scientific/Engineering :: Physics
Classifier: Topic :: Scientific/Engineering :: Visualization
Requires-Python: >=3.12.0
License-File: LICENSE
Requires-Dist: appdirs>=1.4.4
Requires-Dist: h5py>=3.14.0
Requires-Dist: networkx>=3.5
Requires-Dist: numpy>=2.2.6
Requires-Dist: opencv-python-headless>=4.12.0.88
Requires-Dist: packaging>=25.0
Requires-Dist: pathvalidate>=3.3.1
Requires-Dist: periodictable>=2.0.2
Requires-Dist: pillow>=11.3.0
Requires-Dist: PyQt5>=5.15.11
Requires-Dist: pyqtgraph>=0.13.0
Requires-Dist: qdarkgraystyle>=2.0.0
Requires-Dist: QDarkStyle>=3.2.3
Requires-Dist: requests>=2.32.4
Requires-Dist: scipy>=1.16.1
Requires-Dist: tifffile>=2025.6.11
Requires-Dist: typing_extensions>=4.14.1
Requires-Dist: transliterate>=1.10.2
Requires-Dist: xmlobj>=1.2.2
Requires-Dist: xrayutilities>=1.7.10
Dynamic: license-file
